databytes/__init__.py
databytes/types.py
databytes/utils.py
databytes-1.3.dist-info/LICENSE
databytes-1.3.dist-info/METADATA
databytes-1.3.dist-info/WHEEL
databytes-1.3.dist-info/top_level.txt
databytes-1.3.dist-info/zip-safe
databytes-1.3.dist-info/RECORD
