Metadata-Version: 2.1
Name: databytes
Version: 1.3
Summary: A class based binary structure to serialize/deserialize binary data (using python struct under the hood).
Author-email: "Stephane \"Twidi\" Angel" <s.angel@twidi.com>
License: Copyright (c) 2024-present Stéphane "Twidi" Angel.
Project-URL: source, https://github.com/twidi/databytes
Project-URL: author, https://twidi.com
Keywords: binary,struct,data-structures,shared-memory,buffer,serialization,deserialization,memory-mapping,bytes
Platform: Linux
Classifier: Development Status :: 5 - Production/Stable
Classifier: Intended Audience :: Developers
Classifier: License :: OSI Approved :: MIT License
Classifier: Operating System :: POSIX :: Linux
Classifier: Programming Language :: Python
Classifier: Programming Language :: Python :: 3
Classifier: Programming Language :: Python :: 3 :: Only
Classifier: Programming Language :: Python :: 3.10
Classifier: Programming Language :: Python :: 3.11
Classifier: Programming Language :: Python :: 3.12
Requires-Python: >=3.10
License-File: LICENSE
Requires-Dist: typing-extensions
Requires-Dist: numpy
Provides-Extra: extra
Requires-Dist: rich; extra == "extra"
Provides-Extra: dev
Requires-Dist: build; extra == "dev"
Requires-Dist: ruff>=0.1.2; extra == "dev"
Requires-Dist: mypy; extra == "dev"
Requires-Dist: pytest; extra == "dev"
Requires-Dist: pytest-cov; extra == "dev"
Requires-Dist: pytest-env; extra == "dev"
Requires-Dist: pytest-sugar; extra == "dev"
Requires-Dist: twine; extra == "dev"
Requires-Dist: uv; extra == "dev"
